CVAugmentor/__init__.py
CVAugmentor/assets/__init__.py
CVAugmentor/assets/augmentations/__init__.py
CVAugmentor/assets/augmentations/_blur.py
CVAugmentor/assets/augmentations/_brightness.py
CVAugmentor/assets/augmentations/_cutout.py
CVAugmentor/assets/augmentations/_exposure.py
CVAugmentor/assets/augmentations/_flip.py
CVAugmentor/assets/augmentations/_grayscale.py
CVAugmentor/assets/augmentations/_hue.py
CVAugmentor/assets/augmentations/_negative.py
CVAugmentor/assets/augmentations/_no_augmentation.py
CVAugmentor/assets/augmentations/_noise.py
CVAugmentor/assets/augmentations/_rotate.py
CVAugmentor/assets/augmentations/_saturation.py
CVAugmentor/assets/augmentations/_shear.py
CVAugmentor/assets/augmentations/_zoom.py
CVAugmentor/assets/main/__init__.py
CVAugmentor/assets/main/image_augmentor.py
CVAugmentor/assets/main/pipeline.py
CVAugmentor/assets/main/video_augmentor.py
CVAugmentor/assets/main/components/__init__.py
CVAugmentor/assets/main/components/pipeline/__init__.py
CVAugmentor/assets/main/components/pipeline/_apply_augmentations.py
CVAugmentor/assets/main/components/pipeline/_choose_augmentor.py
CVAugmentor/assets/main/components/pipeline/_process_batch.py
CVAugmentor/assets/main/components/pipeline/_process_single.py
CVAugmentor/assets/utils/__init__.py
CVAugmentor/assets/utils/file_type_checker.py
CVAugmentor/assets/utils/sort_alphanumerically.py
CVAugmentor-1.1.2.dist-info/LICENCE
CVAugmentor-1.1.2.dist-info/METADATA
CVAugmentor-1.1.2.dist-info/WHEEL
CVAugmentor-1.1.2.dist-info/top_level.txt
CVAugmentor-1.1.2.dist-info/RECORD
