Metadata-Version: 2.2
Name: CVAugmentor
Version: 1.1.2
Summary: A package for augmenting images and videos for computer vision tasks
Author-email: Ali Khalili Tazehkandgheshlagh <ali.khalili.t98@gmail.com>
License: MIT
Project-URL: Homepage, https://github.com/AliKHaliliT/CVAugmentor
Requires-Python: >=3.12.8
License-File: LICENCE
Requires-Dist: colorama==0.4.6
Requires-Dist: numpy==2.2.2
Requires-Dist: opencv-python==4.11.0.86
Requires-Dist: Pillow==11.1.0
Requires-Dist: tqdm==4.67.1
Provides-Extra: dev
Requires-Dist: unittest; extra == "dev"
